setup.py
kompass/__init__.py
kompass/crawl.py
kompass.egg-info/PKG-INFO
kompass.egg-info/SOURCES.txt
kompass.egg-info/dependency_links.txt
kompass.egg-info/top_level.txt