Metadata-Version: 1.0
Name: kompass
Version: 0.0.0.1
Summary: crawl the kompass
Home-page: https://test.example.com
Author: test
Author-email: 3168095199@qq.com
License: UNKNOWN
Platform: UNKNOWN
